aidkitmlevaluate/__init__.py
aidkitmlevaluate/load_image.py
aidkitmlevaluate/load_model.py
aidkitmlevaluate/read_tfrecord.py
aidkitmlevaluate/utils.py
aidkitmlevaluate-0.1.0.dist-info/METADATA
aidkitmlevaluate-0.1.0.dist-info/WHEEL
aidkitmlevaluate-0.1.0.dist-info/top_level.txt
aidkitmlevaluate-0.1.0.dist-info/RECORD
