Metadata-Version: 2.1
Name: aidkitmlevaluate
Version: 0.1.0
Summary: A test Python package for an interface to evaluate ML models
Home-page: UNKNOWN
Author: Sachin Manjunath
Author-email: sachin.mhegde@gmail.com
License: UNKNOWN
Platform: UNKNOWN
Classifier: Development Status :: 1 - Planning
Classifier: Intended Audience :: Science/Research
Classifier: Operating System :: POSIX :: Linux
Classifier: Programming Language :: Python :: 3
Classifier: Programming Language :: Python :: 3.4
Classifier: Programming Language :: Python :: 3.5
Requires-Dist: tensorflow (>=2.0)
Requires-Dist: numpy
